<?xml version="1.0" encoding="UTF-8"?>
<nrml xmlns:gml="http://www.opengis.net/gml"
      xmlns="http://openquake.org/xmlns/nrml/0.5">
    <logicTree logicTreeID='lt1'>

<!-- Logic Tree for Subduction Interface -->

        <logicTreeBranchingLevel branchingLevelID="bl05">
            <logicTreeBranchSet branchSetID="bs05" uncertaintyType="gmpeModel"
                    applyToTectonicRegionType="Subduction Interface">

                <logicTreeBranch branchID="b51">
                    <uncertaintyModel>AtkinsonBoore2003SInter</uncertaintyModel>
                    <uncertaintyWeight>0.30</uncertaintyWeight>
                </logicTreeBranch>
<!--                 
                <logicTreeBranch branchID="b52">
                    <uncertaintyModel>LinLee2008SInter</uncertaintyModel>
                    <uncertaintyWeight>0.20</uncertaintyWeight>
                </logicTreeBranch>
 -->
                <logicTreeBranch branchID="b53">
                    <uncertaintyModel>AbrahamsonEtAl2015SInter</uncertaintyModel>
                    <uncertaintyWeight>0.30</uncertaintyWeight>
                </logicTreeBranch>
                
                <logicTreeBranch branchID="b53">
                    <uncertaintyModel>ZhaoEtAl2016SInter</uncertaintyModel>
                    <uncertaintyWeight>0.40</uncertaintyWeight>
                </logicTreeBranch>

            </logicTreeBranchSet>
        </logicTreeBranchingLevel> 

    </logicTree>
</nrml>
