{"type": "FeatureCollection", "metadata": {"depth": 13.0, "network": "USGS National Earthquake Information Center, PDE", "id": "usp000h60h", "rake": 0.0, "netid": "us", "time": "2010-01-12T21:53:10.000000Z", "mag": 7.0, "locstring": "Haiti region", "lon": -72.571, "reference": "source: Hayes, G. (2011). USGS NEIC. http://earthquake.usgs.gov/earthquakes/eqinthenews/2010/us2010rja6/finite_fault.php", "lat": 18.443, "mech": "ALL", "productcode": "usp000h60h"}, "features": [{"properties": {"rupture type": "rupture extent"}, "type": "Feature", "geometry": {"type": "MultiPolygon", "coordinates": [[[[-72.4431, 18.4766, 0.4708], [-72.9433, 18.4267, 0.4708], [-72.9515, 18.5007, 23.18], [-72.4513, 18.5506, 23.18], [-72.4431, 18.4766, 0.4708]]]]}}]}